XrayPy-0.1.dist-info/METADATA
XrayPy-0.1.dist-info/RECORD
XrayPy-0.1.dist-info/WHEEL
XrayPy-0.1.dist-info/entry_points.txt
XrayPy-0.1.dist-info/top_level.txt
xraypy/__init__.py
xraypy/xrayapi.py
xraypy/xraycli.py
xraypy/xrayutils.py
