Metadata-Version: 2.1
Name: XrayPy
Version: 0.1
Summary: "Wrapper for Xray's REST API"
Home-page: http://jpsgalego.byethost11.com
Author: JoÃ£o Galego
Author-email: joao.galego@wintrust.tech
License: mit
Platform: any
Classifier: Development Status :: 4 - Beta
Classifier: Programming Language :: Python
